{
  "info": {
    "_postman_id": "676d95c3-e16d-4fc9-9a64-27c5c59066c8",
    "name": "FormManagement",
    "schema": "https://schema.getpostman.com/json/collection/v2.1.0/collection.json"
  },
  "item": [
    {
      "name": "field",
      "item": [
        {
          "name": "get all",
          "id": "933fe27f-bc27-4791-a0cd-6a8b2d52d2c4",
          "request": {
            "method": "GET",
            "header": [],
            "url": {
              "raw": ""
            }
          },
          "response": []
        },
        {
          "name": "create",
          "id": "2f948ae4-712d-4675-94cf-0e929cd49d10",
          "request": {
            "method": "POST",
            "header": [],
            "body": {
              "mode": "raw",
              "raw": "{\r\n    \"label\":\"abc\",\r\n    \"type\":\"NUMBER\",\r\n    \"order\":[\"number\", \"id\"],\r\n    \"required\":true,\r\n    \"options\": []\r\n}",
              "options": {
                "raw": {
                  "language": "json"
                }
              }
            },
            "url": {
              "raw": "http://localhost:8080/api/v1/field",
              "protocol": "http",
              "host": [
                "localhost"
              ],
              "port": "8080",
              "path": [
                "api",
                "v1",
                "field"
              ]
            }
          },
          "response": []
        },
        {
          "name": "update",
          "id": "fc7df5da-0d86-4b7d-8fef-00fb1129c4c9",
          "request": {
            "method": "PUT",
            "header": [],
            "body": {
              "mode": "raw",
              "raw": "{\r\n    \"id\":1,\r\n    \"label\":\"abcde\",\r\n    \"type\":\"NUMBER\",\r\n    \"order\":[\"number\", \"id\"],\r\n    \"required\":true,\r\n    \"options\": []\r\n}",
              "options": {
                "raw": {
                  "language": "json"
                }
              }
            },
            "url": {
              "raw": "http://localhost:8080/api/v1/field",
              "protocol": "http",
              "host": [
                "localhost"
              ],
              "port": "8080",
              "path": [
                "api",
                "v1",
                "field"
              ]
            }
          },
          "response": []
        },
        {
          "name": "get one",
          "id": "17db2b8e-27b2-4fb3-9326-d25963652f96",
          "request": {
            "method": "GET",
            "header": [],
            "url": {
              "raw": "http://localhost:8080/api/v1/field/1",
              "protocol": "http",
              "host": [
                "localhost"
              ],
              "port": "8080",
              "path": [
                "api",
                "v1",
                "field",
                "1"
              ]
            }
          },
          "response": []
        },
        {
          "name": "delete",
          "id": "d4607e60-a7df-43dd-9a7d-39b86c7fea1f",
          "request": {
            "method": "DELETE",
            "header": [],
            "url": {
              "raw": "http://localhost:8080/api/v1/field/1",
              "protocol": "http",
              "host": [
                "localhost"
              ],
              "port": "8080",
              "path": [
                "api",
                "v1",
                "field",
                "1"
              ]
            }
          },
          "response": []
        }
      ],
      "id": "7479db0f-2644-44b2-9a4f-3c76e32e9e6d"
    },
    {
      "name": "form",
      "item": [
        {
          "name": "create",
          "id": "887edb08-841c-4533-acb5-b3326aa91d6c",
          "request": {
            "method": "POST",
            "header": [],
            "body": {
              "mode": "raw",
              "raw": "{\r\n    \"title\":\"abcde\",\r\n    \"description\":\"abcdeasdasdkl\",\r\n    \"order\":[\"number\", \"id\"]\r\n}",
              "options": {
                "raw": {
                  "language": "json"
                }
              }
            },
            "url": {
              "raw": "http://localhost:8080/api/v1/forms",
              "protocol": "http",
              "host": [
                "localhost"
              ],
              "port": "8080",
              "path": [
                "api",
                "v1",
                "forms"
              ]
            }
          },
          "response": []
        },
        {
          "name": "get all",
          "id": "7cd9c99e-0814-4150-8b9e-734be4264796",
          "request": {
            "method": "GET",
            "header": [],
            "url": {
              "raw": "http://localhost:8080/api/v1/forms",
              "protocol": "http",
              "host": [
                "localhost"
              ],
              "port": "8080",
              "path": [
                "api",
                "v1",
                "forms"
              ]
            }
          },
          "response": []
        },
        {
          "name": "get one",
          "id": "494995c7-1b17-4cae-ab4a-4d54248cf815",
          "request": {
            "method": "GET",
            "header": [],
            "url": {
              "raw": ""
            }
          },
          "response": []
        },
        {
          "name": "update",
          "id": "bd496c43-19bc-4d4d-907a-677018a760d6",
          "request": {
            "method": "PATCH",
            "header": [],
            "body": {
              "mode": "raw",
              "raw": "{\r\n    \"id\":1,\r\n    \"title\":\"abcde\",\r\n    \"description\":\"abcdeasdasdkl\",\r\n    \"order\":[\"number\", \"id\"],\r\n    \"status\":\"DRAFT\"\r\n}",
              "options": {
                "raw": {
                  "language": "json"
                }
              }
            },
            "url": {
              "raw": "http://localhost:8080/api/v1/forms",
              "protocol": "http",
              "host": [
                "localhost"
              ],
              "port": "8080",
              "path": [
                "api",
                "v1",
                "forms"
              ]
            }
          },
          "response": []
        },
        {
          "name": "delete",
          "id": "79d85b6f-e48a-4351-b392-406ff40c03bf",
          "request": {
            "method": "GET",
            "header": [],
            "url": {
              "raw": ""
            }
          },
          "response": []
        },
        {
          "name": "add field",
          "id": "b89c036a-c63c-4d03-bdb7-e7f880521276",
          "request": {
            "method": "POST",
            "header": [],
            "body": {
              "mode": "raw",
              "raw": "{\r\n    \"label\":\"baksk\",\r\n    \"type\":\"NUMBER\",\r\n    \"order\":[\"required\", \"id\", \"label\"],\r\n    \"required\":true,\r\n    \"options\": []\r\n}",
              "options": {
                "raw": {
                  "language": "json"
                }
              }
            },
            "url": {
              "raw": "http://localhost:8080/api/v1/forms/2/fields",
              "protocol": "http",
              "host": [
                "localhost"
              ],
              "port": "8080",
              "path": [
                "api",
                "v1",
                "forms",
                "2",
                "fields"
              ]
            }
          },
          "response": []
        },
        {
          "name": "update field of form",
          "id": "d642a02d-6244-4860-876b-eb0a347bc368",
          "request": {
            "method": "GET",
            "header": [],
            "url": {
              "raw": ""
            }
          },
          "response": []
        },
        {
          "name": "delete field of form",
          "id": "758120f4-9c66-4e02-bf0d-ef0c303f135f",
          "request": {
            "method": "GET",
            "header": [],
            "url": {
              "raw": ""
            }
          },
          "response": []
        },
        {
          "name": "get active form",
          "id": "7bde907b-1a28-4988-bf9d-0dbf0db78042",
          "request": {
            "method": "GET",
            "header": [],
            "url": {
              "raw": "http://localhost:8080/api/v1/forms/active",
              "protocol": "http",
              "host": [
                "localhost"
              ],
              "port": "8080",
              "path": [
                "api",
                "v1",
                "forms",
                "active"
              ]
            }
          },
          "response": []
        }
      ],
      "id": "7c9ab429-1efd-4cee-8ea3-45be3a075f14"
    },
    {
      "name": "submission",
      "item": [
        {
          "name": "submit",
          "id": "213eb9bc-b637-457c-8af2-524cfd0b2835",
          "request": {
            "method": "POST",
            "header": [],
            "body": {
              "mode": "raw",
              "raw": "{\r\n  \"fieldValueList\": [\r\n    {\r\n      \"fieldId\": 6,\r\n      \"value\": \"Nguyễn Văn A\"\r\n    },\r\n    {\r\n      \"fieldId\": 7,\r\n      \"value\": \"IT Department\"\r\n    },\r\n    {\r\n      \"fieldId\": 8,\r\n      \"value\": \"Đã hoàn thành task dự án X\"\r\n    }\r\n  ]\r\n}",
              "options": {
                "raw": {
                  "language": "json"
                }
              }
            },
            "url": {
              "raw": "http://localhost:8080/api/v1/forms/2/submit",
              "protocol": "http",
              "host": [
                "localhost"
              ],
              "port": "8080",
              "path": [
                "api",
                "v1",
                "forms",
                "2",
                "submit"
              ]
            }
          },
          "response": []
        },
        {
          "name": "get submitted form",
          "id": "7bfc6da8-88d0-4b50-a85e-3840737afbf8",
          "protocolProfileBehavior": {
            "disableBodyPruning": true
          },
          "request": {
            "method": "GET",
            "header": [],
            "body": {
              "mode": "raw",
              "raw": "{\r\n  \"fieldValueList\": [\r\n    {\r\n      \"fieldId\": 6,\r\n      \"value\": \"Nguyễn Văn A\"\r\n    },\r\n    {\r\n      \"fieldId\": 7,\r\n      \"value\": \"IT Department\"\r\n    },\r\n    {\r\n      \"fieldId\": 8,\r\n      \"value\": \"Đã hoàn thành task dự án X\"\r\n    }\r\n  ]\r\n}"
            },
            "url": {
              "raw": "http://localhost:8080/api/v1/submissions",
              "protocol": "http",
              "host": [
                "localhost"
              ],
              "port": "8080",
              "path": [
                "api",
                "v1",
                "submissions"
              ]
            }
          },
          "response": []
        }
      ],
      "id": "a5081994-2116-4ff7-ba46-ffa53352e7c7"
    }
  ]
}